[
  {
    "profileId": "phone-compact",
    "displayName": "Phone Compact",
    "deviceMode": "single-device",
    "formFactor": "phone",
    "resolution": "1080x2160",
    "ramMb": 2048,
    "storageMb": 4096,
    "defaultLocale": "de-DE",
    "defaultTimezone": "Europe/Berlin",
    "networkProfile": "wifi-stable",
    "playStore": false,
    "snapshotPolicy": "cold-boot-daily"
  },
  {
    "profileId": "phone-standard",
    "displayName": "Phone Standard",
    "deviceMode": "single-device",
    "formFactor": "phone",
    "resolution": "1080x2400",
    "ramMb": 3072,
    "storageMb": 6144,
    "defaultLocale": "de-DE",
    "defaultTimezone": "Europe/Berlin",
    "networkProfile": "wifi-stable",
    "playStore": false,
    "snapshotPolicy": "cold-boot-daily"
  },
  {
    "profileId": "phone-large",
    "displayName": "Phone Large",
    "deviceMode": "single-device",
    "formFactor": "phone",
    "resolution": "1440x3120",
    "ramMb": 4096,
    "storageMb": 8192,
    "defaultLocale": "de-DE",
    "defaultTimezone": "Europe/Berlin",
    "networkProfile": "wifi-stable",
    "playStore": true,
    "snapshotPolicy": "cold-boot-per-run"
  },
  {
    "profileId": "dual-device-low-band",
    "displayName": "Dual Device Low Bandwidth",
    "deviceMode": "dual-device",
    "formFactor": "phone-pair",
    "resolution": "1080x2400",
    "ramMb": 3072,
    "storageMb": 6144,
    "defaultLocale": "de-DE",
    "defaultTimezone": "Europe/Berlin",
    "networkProfile": "wifi-throttled",
    "playStore": false,
    "snapshotPolicy": "cold-boot-per-run"
  },
  {
    "profileId": "dual-device-balanced",
    "displayName": "Dual Device Balanced",
    "deviceMode": "dual-device",
    "formFactor": "phone-pair",
    "resolution": "1080x2400",
    "ramMb": 4096,
    "storageMb": 8192,
    "defaultLocale": "de-DE",
    "defaultTimezone": "Europe/Berlin",
    "networkProfile": "wifi-stable",
    "playStore": false,
    "snapshotPolicy": "cold-boot-per-run"
  },
  {
    "profileId": "dual-device-high-band",
    "displayName": "Dual Device High Bandwidth",
    "deviceMode": "dual-device",
    "formFactor": "phone-pair",
    "resolution": "1440x3120",
    "ramMb": 4096,
    "storageMb": 8192,
    "defaultLocale": "de-DE",
    "defaultTimezone": "Europe/Berlin",
    "networkProfile": "wifi-stable",
    "playStore": true,
    "snapshotPolicy": "cold-boot-per-run"
  }
]
